odoo/addons/purchase_reorder_control/README.rst
odoo/addons/purchase_reorder_control/__init__.py
odoo/addons/purchase_reorder_control/__manifest__.py
odoo/addons/purchase_reorder_control/i18n/fr.po
odoo/addons/purchase_reorder_control/i18n/it.po
odoo/addons/purchase_reorder_control/i18n/purchase_reorder_control.pot
odoo/addons/purchase_reorder_control/models/__init__.py
odoo/addons/purchase_reorder_control/models/product_template.py
odoo/addons/purchase_reorder_control/models/stock_warehouse_orderpoint.py
odoo/addons/purchase_reorder_control/readme/CONTRIBUTORS.rst
odoo/addons/purchase_reorder_control/readme/CREDITS.rst
odoo/addons/purchase_reorder_control/readme/DESCRIPTION.rst
odoo/addons/purchase_reorder_control/static/description/icon.png
odoo/addons/purchase_reorder_control/static/description/index.html
odoo/addons/purchase_reorder_control/tests/__init__.py
odoo/addons/purchase_reorder_control/tests/test_unpurchaseable_product.py
odoo_addon_purchase_reorder_control-16.0.1.0.0.8.dist-info/METADATA
odoo_addon_purchase_reorder_control-16.0.1.0.0.8.dist-info/WHEEL
odoo_addon_purchase_reorder_control-16.0.1.0.0.8.dist-info/top_level.txt
odoo_addon_purchase_reorder_control-16.0.1.0.0.8.dist-info/RECORD
